datastruct/__init__.py
datastruct/common.py
datastruct/ds.py
datastruct/exceptions.py
datastruct/typing_ext.py
datastruct/validators.py
datastruct/test/__init__.py
datastruct/test/test_base.py
datastruct/test/test_common.py
datastruct/test/test_convert.py
datastruct/test/test_generics.py
datastruct/test/test_nested.py
datastruct/test/test_to_serializable_value.py
datastruct/test/test_typing_ext.py
datastruct-0.3.dist-info/AUTHORS
datastruct-0.3.dist-info/LICENSE
datastruct-0.3.dist-info/METADATA
datastruct-0.3.dist-info/WHEEL
datastruct-0.3.dist-info/top_level.txt
datastruct-0.3.dist-info/zip-safe
datastruct-0.3.dist-info/RECORD
